azure/__init__.py
azure/cli/__init__.py
azure/cli/command_modules/__init__.py
azure/cli/command_modules/interactive/__init__.py
azure/cli/command_modules/interactive/color_styles.py
azure/cli/command_modules/interactive/custom.py
azure_cli_interactive-0.4.5.dist-info/METADATA
azure_cli_interactive-0.4.5.dist-info/WHEEL
azure_cli_interactive-0.4.5.dist-info/top_level.txt
azure_cli_interactive-0.4.5.dist-info/RECORD
