Metadata-Version: 2.1
Name: azure-cli-interactive
Version: 0.4.5
Summary: Microsoft Azure Command-Line Interactive Shell
Home-page: https://github.com/Azure/azure-cli
Author: Microsoft Corporation
Author-email: azpycli@microsoft.com
License: MIT
Platform: UNKNOWN
Classifier: Development Status :: 4 - Beta
Classifier: Intended Audience :: Developers
Classifier: Intended Audience :: System Administrators
Classifier: Programming Language :: Python
Classifier: Programming Language :: Python :: 2
Classifier: Programming Language :: Python :: 2.7
Classifier: Programming Language :: Python :: 3
Classifier: Programming Language :: Python :: 3.4
Classifier: Programming Language :: Python :: 3.5
Classifier: Programming Language :: Python :: 3.6
Requires-Dist: azure-cli-core
Requires-Dist: prompt-toolkit (~=1.0.15)
Requires-Dist: azure-cli-command-modules-nspkg (>=2.0.0)
